{
  "project_info": {
    "project_number": "236916747164",
    "project_id": "chatappdemo-420316",
    "storage_bucket": "chatappdemo-420316.appspot.com"
  },
  "client": [
    {
      "client_info": {
        "mobilesdk_app_id": "1:236916747164:android:5165c66f0d87cdedca3659",
        "android_client_info": {
          "package_name": "com.chatappdemo"
        }
      },
      "oauth_client": [
        {
          "client_id": "236916747164-a6eh2sk09tf9sckppnlgak3k1kjvk675.apps.googleusercontent.com",
          "client_type": 3
        }
      ],
      "api_key": [
        {
          "current_key": "AIzaSyDwZC3911a-kQeYpZ0azGKvxNUwdwwnOfk"
        }
      ],
      "services": {
        "appinvite_service": {
          "other_platform_oauth_client": [
            {
              "client_id": "236916747164-a6eh2sk09tf9sckppnlgak3k1kjvk675.apps.googleusercontent.com",
              "client_type": 3
            }
          ]
        }
      }
    }
  ],
  "configuration_version": "1"
}